caroline/__init__.py
caroline/config.py
caroline/databases/__init__.py
caroline/databases/elasticsearch.py
caroline/databases/jsondb.py
caroline/databases/redis.py
caroline/engine.py
caroline/errors.py
caroline/test_engine.py
caroline-0.5.2.dist-info/LICENSE
caroline-0.5.2.dist-info/WHEEL
caroline-0.5.2.dist-info/METADATA
caroline-0.5.2.dist-info/RECORD
